{
  "Service": {
    "name": "EmailService",
    "hostname": "127.0.0.1",
    "port": 4043,
    "debug_mode": true
  },
  "Backend": {
    "hostname": "127.0.0.1",
    "port": 40075
  },
  "Redis": {
    "hostname": "127.0.0.1",
    "port": 6379,
    "db": 0,
    "username": "",
    "password": ""
  },
  "Database": {
    "db_type": "QPSQL",
    "name": "openteraemails",
    "url": "127.0.0.1",
    "port": 5432,
    "username": "teraagent",
    "password": "tera"
  },
  "Email" : {
    "hostname": "127.0.0.1",
	"port": 25,
	"tls": false,
	"ssl": true,
	"username": "username",
	"password": "password",
	"default_sender": "me@opentera.com",
	"max_emails": 25
  }
}